[
	{
		"word": "mawa",
		"meaning": "kiss"
	},
	{
		"word": "binta",
		"meaning": "eat"
	},
	{
		"word": "sanu",
		"meaning": "be"
	},
	{
		"word": "tenco",
		"meaning": "have"
	},
	{
		"word": "somo",
		"meaning": "sleep"
	},
	{
		"word": "cosi",
		"meaning": "choose, vote"
	},
	{
		"word": "falo",
		"meaning": "speak, say, tell"
	},
	{
		"word": "toransu",
		"meaning": "differ"
	},
	{
		"word": "mahen",
		"meaning": "make, create"
	},
	{
		"word": "sekiso",
		"meaning": "have sex, fuck"
	},
	{
		"word": "deja",
		"meaning": "do, act"
	},
	{
		"word": "gade",
		"meaning": "guess"
	},
	{
		"word": "nem",
		"meaning": "think"
	},
	{
		"word": "pen",
		"meaning": "move"
	},
	{
		"word": "nepen",
		"meaning": "feel"
	},
	{
		"word": "gurati",
		"meaning": "induce negative freedom, reduce cost to none"
	},
	{
		"word": "lifeta",
		"meaning": "induce positive freedom"
	},
	{
		"word": "jala",
		"meaning": "can, be able to"
	},
	{
		"word": "meta",
		"meaning": "measure"
	},
	{
		"word": "core",
		"meaning": "want"
	},
	{
		"word": "jore",
		"meaning": "need"
	}
]